aplustools/__init__.py
aplustools/_cli.py
aplustools/_direct.py
aplustools/py.typed
aplustools/data/__init__.py
aplustools/data/_direct.py
aplustools/data/bintools.py
aplustools/data/dummy.py
aplustools/data/storage.py
aplustools/io/__init__.py
aplustools/io/_direct.py
aplustools/io/concurrency.py
aplustools/io/env.py
aplustools/io/fileio.py
aplustools/package/__init__.py
aplustools/package/_direct.py
aplustools/package/autocli.py
aplustools/package/chronokit.py
aplustools/security/__init__.py
aplustools/security/_direct.py
aplustools/security/passwords.py
aplustools/security/rand.py
aplustools/security/crypto/__init__.py
aplustools/security/crypto/_argon2_cffi.py
aplustools/security/crypto/_bcrypt.py
aplustools/security/crypto/_definitions.py
aplustools/security/crypto/_std_lib.py
aplustools/security/crypto/exceptions.py
aplustools/security/crypto/_crypto_alpha/__init__.py
aplustools/security/crypto/_crypto_alpha/_keys.py
aplustools/security/crypto/_crypto_alpha/_others.py
aplustools/security/crypto/_pycrypto_alpha/__init__.py
aplustools/security/crypto/_quantcrypt/__init__.py
aplustools/security/crypto/algos/__init__.py
aplustools/security/crypto/algos/_key_derivation_function.py
aplustools/security/crypto/algos/_asym/__init__.py
aplustools/security/crypto/algos/_asym/_cipher.py
aplustools/security/crypto/algos/_hash_algorithm/__init__.py
aplustools/security/crypto/algos/_hash_algorithm/_blake2.py
aplustools/security/crypto/algos/_hash_algorithm/_sha2.py
aplustools/security/crypto/algos/_hash_algorithm/_sha3.py
aplustools/security/crypto/algos/_sym/__init__.py
aplustools/security/crypto/algos/_sym/_cipher.py
aplustools/security/dicts/def-dict.txt
aplustools/security/dicts/google-10000-dict.txt
aplustools/security/dicts/scowl-50-dict.txt
aplustools/security/dicts/scowl-60-dict.txt
aplustools/security/dicts/scowl-70-dict.txt
aplustools/security/dicts/scowl-80-dict.txt
aplustools/security/dicts/scowl-95-dict.txt
aplustools/security/dicts/12-dicts/2of12.txt
aplustools-2.0.0.5.dist-info/licenses/LICENSE
aplustools-2.0.0.5.dist-info/METADATA
aplustools-2.0.0.5.dist-info/WHEEL
aplustools-2.0.0.5.dist-info/entry_points.txt
aplustools-2.0.0.5.dist-info/top_level.txt
aplustools-2.0.0.5.dist-info/RECORD
