Metadata-Version: 2.4
Name: aplustools
Version: 2.0.0.5
Summary: A collection of helpful tools
Author-email: Cariel Becker <cariel.becker@gmx.de>
Maintainer-email: Cariel Becker <cariel.becker@gmx.de>
License-Expression: LGPL-2.1-or-later
Project-URL: Home, https://pypi.org/project/aplustools/
Project-URL: Repository, https://github.com/adalfarus/aplustools
Project-URL: Documentation, https://github.com/adalfarus/aplustools/wiki
Project-URL: Issue tracker, https://github.com/adalfarus/aplustools/issues
Keywords: general,tools,app tools,production,apt
Classifier: Development Status :: 5 - Production/Stable
Classifier: Programming Language :: Python
Classifier: Natural Language :: English
Requires-Python: >=3.10
License-File: LICENSE
Requires-Dist: packaging
Requires-Dist: pywin32>=306; os_name == "nt"
Requires-Dist: cachetools>=5.5.0
Requires-Dist: typing_extensions
Provides-Extra: data
Requires-Dist: Pillow>=10.3.0; extra == "data"
Requires-Dist: opencv-python>=4.9.0.80; extra == "data"
Requires-Dist: pillow_heif==0.15.0; extra == "data"
Requires-Dist: numpy==1.26.4; extra == "data"
Requires-Dist: brotli>=1.1.0; extra == "data"
Requires-Dist: zstandard>=0.22.0; extra == "data"
Requires-Dist: py7zr>=0.21.0; extra == "data"
Requires-Dist: requests>=2.32.0; extra == "data"
Requires-Dist: BeautifulSoup4>=4.12.2; extra == "data"
Requires-Dist: cachetools>=5.5.0; extra == "data"
Provides-Extra: io
Requires-Dist: windows-toasts>=1.1.1; os_name == "nt" and extra == "io"
Requires-Dist: psutil>=6.0.0; extra == "io"
Requires-Dist: pywin32>=306; extra == "io"
Requires-Dist: PySide6>=6.7.0; extra == "io"
Provides-Extra: package
Requires-Dist: numpy>=1.26.4; extra == "package"
Requires-Dist: scipy>=1.13.0; extra == "package"
Requires-Dist: scikit-learn>=1.5.2; extra == "package"
Provides-Extra: security
Requires-Dist: cryptography>=42.0.5; extra == "security"
Requires-Dist: quantcrypt>=0.4.2; python_version == "3.12" and extra == "security"
Requires-Dist: zxcvbn>=4.4.28; extra == "security"
Requires-Dist: bcrypt>=4.1.2; extra == "security"
Provides-Extra: web
Requires-Dist: requests>=2.32.0; extra == "web"
Requires-Dist: BeautifulSoup4>=4.12.2; extra == "web"
Requires-Dist: aiohttp>=3.9.5; extra == "web"
Provides-Extra: dev
Requires-Dist: pytest; extra == "dev"
Requires-Dist: coverage; extra == "dev"
Requires-Dist: pre-commit; extra == "dev"
Requires-Dist: ruff; extra == "dev"
Requires-Dist: pdoc>=14.0; extra == "dev"
Provides-Extra: all
Requires-Dist: Pillow>=10.4.0; extra == "all"
Requires-Dist: aiohttp>=3.9.4; extra == "all"
Requires-Dist: opencv-python>=4.9.0.80; extra == "all"
Requires-Dist: pillow_heif>=0.15.0; extra == "all"
Requires-Dist: numpy>=1.26.4; extra == "all"
Requires-Dist: brotli>=1.1.0; extra == "all"
Requires-Dist: zstandard>=0.22.0; extra == "all"
Requires-Dist: py7zr>=0.21.0; extra == "all"
Requires-Dist: requests>=2.32.0; extra == "all"
Requires-Dist: BeautifulSoup4>=4.12.2; extra == "all"
Requires-Dist: windows-toasts>=1.1.1; os_name == "nt" and extra == "all"
Requires-Dist: scipy>=1.13.0; extra == "all"
Requires-Dist: scikit-learn>=1.4.1.post1; os_name == "nt" and extra == "all"
Requires-Dist: scikit-learn; os_name != "nt" and extra == "all"
Requires-Dist: cryptography>=42.0.5; extra == "all"
Requires-Dist: quantcrypt>=0.4.2; python_version == "3.12" and extra == "all"
Requires-Dist: pytest; extra == "all"
Requires-Dist: zxcvbn>=4.4.28; extra == "all"
Requires-Dist: bcrypt>=4.1.2; extra == "all"
Requires-Dist: psutil>=6.0.0; extra == "all"
Requires-Dist: pywin32>=306; os_name == "nt" and extra == "all"
Requires-Dist: cachetools>=5.5.0; extra == "all"
Requires-Dist: PySide6>=6.7.0; extra == "all"
Dynamic: license-file
